{
  "recruitment": {
    "timestamp": "2025-09-11T06:23:23.526077+00:00",
    "name": "recruitment",
    "updatedAt": "2025-09-11",
    "records": {}
  },
  "recruitment_table": {
    "timestamp": "2025-09-11T06:23:23.526080+00:00",
    "name": "recruitment_table",
    "updatedAt": "2025-09-11",
    "records": {}
  },
  "chara_skills": {
    "timestamp": "2025-09-11T06:23:23.526047+00:00",
    "name": "chara_skills",
    "newSkills": 574
  },
  "chara_talents": {
    "timestamp": "2025-09-11T06:23:23.526068+00:00",
    "name": "chara_talents",
    "newCharas": 0
  },
  "uniequip": {
    "timestamp": "2025-09-11T06:23:23.526072+00:00",
    "name": "uniequip",
    "newEquips": 0
  },
  "tokens": {
    "timestamp": "2025-09-11T06:23:23.526075+00:00",
    "name": "tokens",
    "newTokens": 53
  },
  "characters": {
    "timestamp": "2025-09-11T06:23:23.526082+00:00",
    "name": "characters",
    "records": {
      "characters exclusive in China": [
        "CONFESS-47",
        "Windscoot",
        "Matsukiri",
        "Gracebearer",
        "Yūtenji Nyamu",
        "Kichisei",
        "Miss.Christine",
        "Record Keeper",
        "Alanna",
        "Misumi Uika",
        "Yahata Umiri",
        "Wakaba Mutsumi",
        "Tippi",
        "Lemuen",
        "Raidian",
        "Haruka",
        "Tragodia",
        "Exusiai the New Covenant",
        "Mon3tr",
        "Sankta Miksaparato",
        "Hoshiguma the Breacher",
        "Togawa Sakiko",
        "Leizi the Thunderbringer"
      ]
    }
  }
}